doc/conf.py
nxtomomill/__init__.py
nxtomomill/__main__.py
nxtomomill/settings.py
nxtomomill/test.py
nxtomomill/version.py
nxtomomill/app/__init__.py
nxtomomill/app/blissfluo2nx.py
nxtomomill/app/blissfluoconfig.py
nxtomomill/app/dxfile2nx.py
nxtomomill/app/edf2nx.py
nxtomomill/app/edf2nx_check.py
nxtomomill/app/edfconfig.py
nxtomomill/app/fluo2nx.py
nxtomomill/app/fluoconfig.py
nxtomomill/app/fscan2nx.py
nxtomomill/app/h52nx.py
nxtomomill/app/h5config.py
nxtomomill/app/nxcopy.py
nxtomomill/app/patch_nx.py
nxtomomill/app/split_nxfile.py
nxtomomill/app/z_concatenate_scans.py
nxtomomill/app/zstages2nxs.py
nxtomomill/app/tests/test_bliss_fluo2nx_app.py
nxtomomill/app/tests/test_dxfile2nx_app.py
nxtomomill/app/tests/test_edf2nx_app.py
nxtomomill/app/tests/test_edf_config_app.py
nxtomomill/app/tests/test_fluo2nx_app.py
nxtomomill/app/tests/test_h52nx_app.py
nxtomomill/app/tests/test_h5_config_app.py
nxtomomill/app/tests/test_nx_copy.py
nxtomomill/app/tests/test_patch_nx_app.py
nxtomomill/app/tests/test_split_nxfile_app.py
nxtomomill/converter/__init__.py
nxtomomill/converter/baseconverter.py
nxtomomill/converter/version.py
nxtomomill/converter/dxfile/__init__.py
nxtomomill/converter/dxfile/dxfileconverter.py
nxtomomill/converter/dxfile/tests/test_dxfile.py
nxtomomill/converter/edf/__init__.py
nxtomomill/converter/edf/checks.py
nxtomomill/converter/edf/edfconverter.py
nxtomomill/converter/edf/tests/test_checks.py
nxtomomill/converter/edf/tests/test_edf2nx.py
nxtomomill/converter/edf/tests/test_edf2nx_check.py
nxtomomill/converter/fluo/__init__.py
nxtomomill/converter/fluo/blissfluoscan.py
nxtomomill/converter/fluo/fluoconverter.py
nxtomomill/converter/fluo/fluoscan.py
nxtomomill/converter/fluo/tests/__init__.py
nxtomomill/converter/fluo/tests/test_fluoscan2D.py
nxtomomill/converter/fluo/tests/test_fluoscan3D.py
nxtomomill/converter/fscan/__init__.py
nxtomomill/converter/fscan/fscanconverter.py
nxtomomill/converter/hdf5/__init__.py
nxtomomill-2.0.1.dist-info/licenses/LICENSE
nxtomomill-2.0.1.dist-info/METADATA
nxtomomill-2.0.1.dist-info/WHEEL
nxtomomill-2.0.1.dist-info/entry_points.txt
nxtomomill-2.0.1.dist-info/top_level.txt
nxtomomill-2.0.1.dist-info/RECORD
