Metadata-Version: 2.4
Name: nxtomomill
Version: 2.0.1
Summary: applications and library to convert raw format to NXtomo format
Author-email: Henri Payno <henri.payno@esrf.fr>, Pierre Paleo <pierre.paleo@esrf.fr>, Pierre-Olivier Autran <pierre-olivier.autran@esrf.fr>, Jérôme Lesaint <jerome.lesaint@esrf.fr>, Alessandro Mirone <mirone@esrf.fr>
License: 
Project-URL: Homepage, https://gitlab.esrf.fr/tomotools/nxtomomill
Project-URL: Documentation, https://tomotools.gitlab-pages.esrf.fr/nxtomomill/
Project-URL: Repository, https://gitlab.esrf.fr/tomotools/nxtomomill
Project-URL: Changelog, https://gitlab.esrf.fr/tomotools/nxtomomill/-/blob/master/CHANGELOG.md
Keywords: NXtomo,nexus,tomography,tomotools,esrf,bliss-tomo
Classifier: Intended Audience :: Education
Classifier: Intended Audience :: Science/Research
Classifier: License :: OSI Approved :: MIT License
Classifier: Programming Language :: Python :: 3
Classifier: Programming Language :: Python :: 3.10
Classifier: Programming Language :: Python :: 3.11
Classifier: Programming Language :: Python :: 3.12
Classifier: Programming Language :: Python :: 3.13
Classifier: Environment :: Console
Classifier: Environment :: X11 Applications :: Qt
Classifier: Operating System :: POSIX
Classifier: Natural Language :: English
Classifier: Topic :: Scientific/Engineering :: Physics
Classifier: Topic :: Software Development :: Libraries :: Python Modules
Requires-Python: >=3.10
License-File: LICENSE
Requires-Dist: numpy
Requires-Dist: h5py>=3.0
Requires-Dist: silx>=2.0
Requires-Dist: nxtomo>=3.0.0dev0
Requires-Dist: pint
Requires-Dist: packaging
Requires-Dist: tomoscan[full]>=2.2.0a4
Requires-Dist: tqdm
Requires-Dist: pydantic
Requires-Dist: eval_type_backport; python_version < "3.10"
Provides-Extra: test
Requires-Dist: pytest; extra == "test"
Requires-Dist: python-gitlab; extra == "test"
Provides-Extra: doc
Requires-Dist: pytest; extra == "doc"
Requires-Dist: Sphinx<5.2.0,>=4.0.0; extra == "doc"
Requires-Dist: nbsphinx; extra == "doc"
Requires-Dist: pandoc; extra == "doc"
Requires-Dist: ipykernel; extra == "doc"
Requires-Dist: jupyter_client; extra == "doc"
Requires-Dist: nbconvert; extra == "doc"
Requires-Dist: scikit-image; extra == "doc"
Requires-Dist: h5glance; extra == "doc"
Requires-Dist: pydata_sphinx_theme; extra == "doc"
Requires-Dist: sphinx-design; extra == "doc"
Requires-Dist: sphinx-autodoc-typehints; extra == "doc"
Requires-Dist: sphinxcontrib-programoutput; extra == "doc"
Requires-Dist: myst-parser; extra == "doc"
Dynamic: license-file
